README.md
setup.py
twitter_auto_post_like_bot/__init__.py
twitter_auto_post_like_bot.egg-info/PKG-INFO
twitter_auto_post_like_bot.egg-info/SOURCES.txt
twitter_auto_post_like_bot.egg-info/dependency_links.txt
twitter_auto_post_like_bot.egg-info/requires.txt
twitter_auto_post_like_bot.egg-info/top_level.txt